lnoise/__init__.py
lnoise/dh_secp256k1.py
lnoise/error.py
lnoise/noisetypes.py
lnoise/patterns.py
lnoise/state.py
lnoise-0.1.1.dist-info/LICENSE.txt
lnoise-0.1.1.dist-info/METADATA
lnoise-0.1.1.dist-info/WHEEL
lnoise-0.1.1.dist-info/top_level.txt
lnoise-0.1.1.dist-info/RECORD
