Metadata-Version: 2.1
Name: lnoise
Version: 0.1.1
Summary: Noise Protocol Framework library compatible with bitcoin lightning transport protocol
Home-page: https://github.com/WTRMQDev/lnoise
Author: Crez Khansick
Author-email: TetsuwanAtomu@tuta.io
License: UNKNOWN
Platform: UNKNOWN
Classifier: Programming Language :: Python :: 3
Classifier: Development Status :: 4 - Beta
Classifier: Intended Audience :: Developers
Classifier: License :: OSI Approved :: MIT License
Classifier: Operating System :: OS Independent
Requires-Dist: chacha20poly1305
Requires-Dist: secp256k1-zkp
